Datapath_design/datapath.v
module datapath(eqz, lda, ldb, ldp, decb, clrp,  DataIn, clk);
input [15:0]DataIn;
input lda, ldb, ldp, clrp, decb, clk;
output eqz;
wire [15:0] A, B, C, Bout, bus;

// a, b, p are the registers in which data is stored
PIPO1 a(A, bus, lda, clk);
PIPO p(B, C, ldp, clrp, clk);
CNTR b(Bout, bus, ldb, decb, clk);
ADD ad(C, A, B);
EQZ eq(eqz, Bout);
endmodule

// module for register A
module PIPO1(dout, din, ld, clk);
input [15:0] din;
input ld, clk;
output reg [15:0] dout;
always @ (posedge clk)
    if (ld) dout <= din;
endmodule

// module for register B
module CNTR(dout, din, ld, dec, clk);
input [15:0]din;
input ld, dec, clk;
output reg [15:0]dout;
always @(posedge clk)
    if(ld) dout <= din;
    else if (dec) dout <= dout - 1; // order can be changed in 'if' block
endmodule

// module for register P
module PIPO(dout, din, ld, clr, clk);
input [15:0] din;
input ld, clr, clk;
output reg [15:0] dout;
always @(posedge clk)
    if(clr) dout <= 16'b0;
    else if (ld) dout <= din;
endmodule

// module for adder block
module ADD(out, in1, in2);
input [15:0] in1, in2;
output reg [15:0]out;
always @(*)
    out = in1 + in2;
endmodule

// module for comparator
module EQZ(eqz, data);
input [15:0]data;
output eqz;
assign eqz = (data == 0);
// assign eqz = ~|data;
endmodule

// module for controller
module controller(lda, ldb, ldp, clrp, decb, done, clk, eqz, start);
input clk, eqz, start;
output reg lda, ldb, ldp, clrp, decb, done;
reg [2:0] state = s0;

parameter s0 = 3'b000, s1 = 3'b001, s2 = 3'b010, s3 = 3'b011, s4 = 3'b100;
always @(posedge clk)
    begin
      case (state)
        s0: if (start) state <= s1;
        s1: state <= s2;
        s2: state <= s3;
        s3: #2 if(eqz) state <= s4;
        s4: state <= s4;
        default: state <= s0;
      endcase
    end
always @(state)
    begin
      case (state)
        s0: begin #1 lda=0; ldb=0; ldp=0; clrp=0; decb=0; end 
        s1: begin #1 lda=1; end
        s2: begin #1 lda=0; ldb=1; clrp=1; end
        s3: begin #1 ldb=0; ldp=1; clrp=0; decb=1; end
        s4: begin #1 done=1; ldb=0; ldp=0; decb=0; end
      default: begin #1 lda=0; ldb=0; ldp=0; clrp=0; decb=0; end
      endcase
    end
endmodule


// testbench module 
module controller_tb;
reg [15:0] DataIn;
reg clk, start;
wire done, eqz;
wire lda, ldb, ldp, clrp, decb;

datapath DP(eqz, lda, ldb, ldp, decb, clrp, DataIn, clk);
controller CON(lda, ldb, ldp, clrp, decb, done, clk, eqz, start);

initial begin
  clk = 1'b0;
  #3 start = 1'b1;
  #500 $finish;
end

always #5 clk = ~clk;

initial begin
  #10 DataIn = 17;
  #10 DataIn = 5;
end

initial begin
  $monitor($time, "%d %b", DP.B, done);
  $dumpfile("controller.vcd");
  $dumpvars(0, controller_tb);
end
endmodule

Datapath_design/controller.vcd
$date
	Fri Mar 07 19:44:38 2025
$end
$version
	Icarus Verilog
$end
$timescale
	1s
$end
$scope module controller_tb $end
$var wire 1 ! ldp $end
$var wire 1 " ldb $end
$var wire 1 # lda $end
$var wire 1 $ eqz $end
$var wire 1 % done $end
$var wire 1 & decb $end
$var wire 1 ' clrp $end
$var reg 16 ( DataIn [15:0] $end
$var reg 1 ) clk $end
$var reg 1 * start $end
$scope module CON $end
$var wire 1 ) clk $end
$var wire 1 * start $end
$var wire 1 $ eqz $end
$var parameter 3 + s0 $end
$var parameter 3 , s1 $end
$var parameter 3 - s2 $end
$var parameter 3 . s3 $end
$var parameter 3 / s4 $end
$var reg 1 ' clrp $end
$var reg 1 & decb $end
$var reg 1 % done $end
$var reg 1 # lda $end
$var reg 1 " ldb $end
$var reg 1 ! ldp $end
$var reg 3 0 state [2:0] $end
$upscope $end
$scope module DP $end
$var wire 16 1 DataIn [15:0] $end
$var wire 16 2 bus [15:0] $end
$var wire 1 ) clk $end
$var wire 1 ' clrp $end
$var wire 1 & decb $end
$var wire 1 # lda $end
$var wire 1 " ldb $end
$var wire 1 ! ldp $end
$var wire 1 $ eqz $end
$var wire 16 3 C [15:0] $end
$var wire 16 4 Bout [15:0] $end
$var wire 16 5 B [15:0] $end
$var wire 16 6 A [15:0] $end
$scope module a $end
$var wire 1 ) clk $end
$var wire 16 7 din [15:0] $end
$var wire 1 # ld $end
$var reg 16 8 dout [15:0] $end
$upscope $end
$scope module ad $end
$var wire 16 9 in1 [15:0] $end
$var wire 16 : in2 [15:0] $end
$var reg 16 ; out [15:0] $end
$upscope $end
$scope module b $end
$var wire 1 ) clk $end
$var wire 1 & dec $end
$var wire 16 < din [15:0] $end
$var wire 1 " ld $end
$var reg 16 = dout [15:0] $end
$upscope $end
$scope module eq $end
$var wire 16 > data [15:0] $end
$var wire 1 $ eqz $end
$upscope $end
$scope module p $end
$var wire 1 ) clk $end
$var wire 1 ' clr $end
$var wire 16 ? din [15:0] $end
$var wire 1 ! ld $end
$var reg 16 @ dout [15:0] $end
$upscope $end
$upscope $end
$upscope $end
$enddefinitions $end
$comment Show the parameter values. $end
$dumpall
b100 /
b11 .
b10 -
b1 ,
b0 +
$end
#0
$dumpvars
bx @
bx ?
bx >
bx =
bz <
bx ;
bx :
bx 9
bx 8
bz 7
bx 6
bx 5
bx 4
bx 3
bz 2
bx 1
b0 0
x*
0)
bx (
x'
x&
x%
x$
x#
x"
x!
$end
#1
0&
0'
0!
0"
0#
#3
1*
#5
b1 0
1)
#6
1#
#10
0)
b10001 (
b10001 1
#15
b10 0
bz 6
bz 8
bz 9
1)
#16
1'
1"
0#
#20
0)
b101 (
b101 1
#25
b0 5
b0 :
b0 @
bz 4
bz =
bz >
b11 0
1)
#26
1&
0'
1!
0"
#30
0)
#35
bx 4
bx =
bx >
bx 5
bx :
bx @
1)
